voyado_engage_sdk/__init__.py
voyado_engage_sdk/sdk.py
voyado_engage_sdk/hooks/__init__.py
voyado_engage_sdk/hooks/hook.py
voyado_engage_sdk/models/__init__.py
voyado_engage_sdk/models/add_checkpoint_to_challenge_assignment_result.py
voyado_engage_sdk/models/all_bonus_check_model.py
voyado_engage_sdk/models/all_loyalty_bar_claim_model.py
voyado_engage_sdk/models/api_achievement_definition.py
voyado_engage_sdk/models/api_achievement_value.py
voyado_engage_sdk/models/api_adjust_reward_points.py
voyado_engage_sdk/models/api_adjust_reward_points_response.py
voyado_engage_sdk/models/api_consent_definition.py
voyado_engage_sdk/models/api_message.py
voyado_engage_sdk/models/api_promotion_model.py
voyado_engage_sdk/models/api_promotion_redemption_channel_model.py
voyado_engage_sdk/models/api_store.py
voyado_engage_sdk/models/assign_date_range.py
voyado_engage_sdk/models/available_bonus_check_model.py
voyado_engage_sdk/models/available_loyalty_bar_claim_model.py
voyado_engage_sdk/models/base.py
voyado_engage_sdk/models/bonus_point_transaction_model.py
voyado_engage_sdk/models/bool_request.py
voyado_engage_sdk/models/cart_api_model.py
voyado_engage_sdk/models/cart_item_api_model.py
voyado_engage_sdk/models/challenge_assignment_model.py
voyado_engage_sdk/models/challenge_assignment_models_result.py
voyado_engage_sdk/models/challenge_check_point_dto.py
voyado_engage_sdk/models/challenge_definition_model.py
voyado_engage_sdk/models/challenge_definition_models_result.py
voyado_engage_sdk/models/challenge_get_challenge_definitions_status.py
voyado_engage_sdk/models/challenge_get_challenges_filter.py
voyado_engage_sdk/models/change_type.py
voyado_engage_sdk/models/contact_search_result.py
voyado_engage_sdk/models/enrichment_variable.py
voyado_engage_sdk/models/enrichment_variable_group.py
voyado_engage_sdk/models/hypermedia_link.py
voyado_engage_sdk/models/i_api_consent.py
voyado_engage_sdk/models/i_api_contact.py
voyado_engage_sdk/models/i_hypermedia_link.py
voyado_engage_client-1.0.0.dist-info/LICENSE
voyado_engage_client-1.0.0.dist-info/METADATA
voyado_engage_client-1.0.0.dist-info/WHEEL
voyado_engage_client-1.0.0.dist-info/top_level.txt
voyado_engage_client-1.0.0.dist-info/RECORD
